[{
        "id": "01",
        "qustion": "Whta is HTML",
        "tag": "html",
        "desc": "HTML is a Hyper text mark up language",
        "code_status": false,
        "code": null
    },
    {
        "id": "02",
        "qustion": "Whta is JS",
        "tag": "js",
        "desc": "HTML is a Hyper text mark up language",
        "code_status": false,
        "code": null
    },
    {
        "id": "03",
        "qustion": "Whta is HTML",
        "tag": "html",
        "desc": "HTML is a Hyper text mark up language",
        "code_status": false,
        "code": null
    },
    {
        "id": "04",
        "qustion": "Whta is HTML",
        "tag": "html",
        "desc": "HTML is a Hyper text mark up language",
        "code_status": false,
        "code": null
    },
    {
        "id": "05",
        "qustion": "Whta is JS",
        "tag": "js",
        "desc": "HTML is a Hyper text mark up language",
        "code_status": false,
        "code": null
    },
    {
        "id": "06",
        "qustion": "Whta is JS",
        "tag": "js",
        "desc": "JS is a Hyper text mark up language",
        "code_status": false,
        "code": null
    },
    {
        "id": "07",
        "qustion": "Whta is REACT",
        "tag": "react",
        "desc": "REACT is a Hyper text mark up language",
        "code_status": false,
        "code": null
    },
    {
        "id": "08",
        "qustion": "Whta is CSS",
        "tag": "css",
        "desc": "CSS is a Hyper text mark up language",
        "code_status": false,
        "code": null
    },
    {
        "id": "09",
        "qustion": "Whta is react",
        "tag": "react",
        "desc": "HTML is a Hyper text mark up language",
        "code_status": false,
        "code": null
    }
]